decentmesh-0.0.166.dist-info/licenses/LICENSE.md
decentnet/__init__.py
decentnet/__version__.py
decentnet/main.py
decentnet/cli/__init__.py
decentnet/cli/client.py
decentnet/cli/keys.py
decentnet/cli/service.py
decentnet/consensus/__init__.py
decentnet/consensus/beam2beam.py
decentnet/consensus/beam_constants.py
decentnet/consensus/block_sizing.py
decentnet/consensus/blockchain_params.py
decentnet/consensus/byte_conversion_constants.py
decentnet/consensus/cmd_enum.py
decentnet/consensus/compress_params.py
decentnet/consensus/dev_constants.py
decentnet/consensus/difficulty_byte_sizing.py
decentnet/consensus/difficulty_ports_mapping.py
decentnet/consensus/env_convert_funcs.py
decentnet/consensus/hashing_params.py
decentnet/consensus/interface_constants.py
decentnet/consensus/local_config.py
decentnet/consensus/metrics_constants.py
decentnet/consensus/net_constants.py
decentnet/consensus/r2rcomm.py
decentnet/consensus/relay_config.py
decentnet/consensus/routing_params.py
decentnet/consensus/share_server_config.py
decentnet/consensus/tcp_params.py
decentnet/interface/__init__.py
decentnet/interface/alias_resolver.py
decentnet/interface/basic.py
decentnet/modules/__init__.py
decentnet/modules/banner/__init__.py
decentnet/modules/banner/banner.py
decentnet/modules/blockchain/__init__.py
decentnet/modules/blockchain/block.py
decentnet/modules/blockchain/blockchain.py
decentnet/modules/blockchain/hasht.py
decentnet/modules/comm/__init__.py
decentnet/modules/comm/beacon.py
decentnet/modules/comm/beam.py
decentnet/modules/comm/block_assembly.py
decentnet/modules/comm/db_funcs.py
decentnet/modules/comm/relay.py
decentnet/modules/compression/__init__.py
decentnet/modules/compression/hbw_wrapper.py
decentnet/modules/compression/zl_wrapper.py
decentnet/modules/convert/__init__.py
decentnet/modules/convert/byte_operations.py
decentnet/modules/convert/byte_to_base64_utils.py
decentnet/modules/cryptography/__init__.py
decentnet/modules/cryptography/asym_man.py
decentnet/modules/cryptography/asymmetric.py
decentmesh-0.0.166.dist-info/METADATA
decentmesh-0.0.166.dist-info/WHEEL
decentmesh-0.0.166.dist-info/entry_points.txt
decentmesh-0.0.166.dist-info/top_level.txt
decentmesh-0.0.166.dist-info/zip-safe
decentmesh-0.0.166.dist-info/RECORD
