Metadata-Version: 2.4
Name: decentmesh
Version: 0.0.166
Summary: Simple connection over decentralized network
Home-page: https://github.com/jiri-otoupal/DecentNet-Py
Author: Jiri Otoupal
Author-email: jiri-otoupal@ips-database.eu
License: JO-CAL
Keywords: Decentralized P2P Network
Classifier: Development Status :: 4 - Beta
Classifier: Intended Audience :: Developers
Classifier: Programming Language :: Python :: 3.8
Classifier: Programming Language :: Python :: 3.9
Classifier: Programming Language :: Python :: 3.10
Classifier: Programming Language :: Python :: 3.11
Classifier: Programming Language :: Python :: 3.12
Classifier: Programming Language :: Python :: 3.13
Requires-Python: >=3.8,<4
License-File: LICENSE.md
Requires-Dist: alembic~=1.16.4
Requires-Dist: argon2-cffi~=25.1.0
Requires-Dist: argon2-cffi-bindings~=25.1.0
Requires-Dist: asn1crypto~=1.5.1
Requires-Dist: cffi~=1.17.1
Requires-Dist: coincurve~=21.0.0
Requires-Dist: pycryptodome~=3.23.0
Requires-Dist: pynacl~=1.5.0
Requires-Dist: eth-utils~=5.1.0
Requires-Dist: lz4~=4.4.4
Requires-Dist: networkx~=3.5
Requires-Dist: SQLAlchemy~=2.0.43
Requires-Dist: cbor2~=5.7.0
Requires-Dist: netifaces~=0.11.0
Requires-Dist: sentry-sdk~=2.16.0
Provides-Extra: async-db
Requires-Dist: greenlet~=3.1.1; extra == "async-db"
Requires-Dist: aiosqlite~=0.21.0; extra == "async-db"
Provides-Extra: dev
Requires-Dist: setuptools~=74.1.2; extra == "dev"
Requires-Dist: black==22.*; extra == "dev"
Requires-Dist: numpy~=2.1.2; extra == "dev"
Provides-Extra: metrics
Requires-Dist: typing_extensions; extra == "metrics"
Requires-Dist: hypercorn~=0.17.3; extra == "metrics"
Requires-Dist: prometheus_client~=0.20.0; extra == "metrics"
Requires-Dist: httpx~=0.27.2; extra == "metrics"
Requires-Dist: mdurl~=0.1.2; extra == "metrics"
Requires-Dist: aiohttp~=3.11.11; extra == "metrics"
Requires-Dist: Mako~=1.3.5; extra == "metrics"
Requires-Dist: markdown-it-py~=3.0.0; extra == "metrics"
Requires-Dist: MarkupSafe~=2.1.5; extra == "metrics"
Provides-Extra: cli
Requires-Dist: click~=8.2.1; extra == "cli"
Requires-Dist: rich~=13.9.2; extra == "cli"
Requires-Dist: colorama~=0.4.6; extra == "cli"
Requires-Dist: Pygments~=2.18.0; extra == "cli"
Requires-Dist: six~=1.16.0; extra == "cli"
Requires-Dist: qrcode~=8.0; extra == "cli"
Dynamic: author
Dynamic: author-email
Dynamic: classifier
Dynamic: description
Dynamic: description-content-type
Dynamic: home-page
Dynamic: keywords
Dynamic: license
Dynamic: license-file
Dynamic: provides-extra
Dynamic: requires-dist
Dynamic: requires-python
Dynamic: summary
